toxolib/__init__.py
toxolib/abundance_matrix.py
toxolib/cli.py
toxolib/database.py
toxolib/hpc.py
toxolib/session.py
toxolib/data/Snakefile
toxolib/data/create_abundance_matrix.py
toxolib/data/environment.yml
toxolib-0.1.42.dist-info/licenses/LICENSE
toxolib-0.1.42.dist-info/METADATA
toxolib-0.1.42.dist-info/WHEEL
toxolib-0.1.42.dist-info/entry_points.txt
toxolib-0.1.42.dist-info/top_level.txt
toxolib-0.1.42.dist-info/RECORD
