Metadata-Version: 2.4
Name: toxolib
Version: 0.1.42
Summary: A tool for metagenomic taxonomic profiling and abundance matrix generation
Home-page: https://github.com/dhruvac29/toxolib
Author: Dhruvil Chodvadiya
Author-email: dhruvac29@gmail.com
Classifier: Programming Language :: Python :: 3
Classifier: License :: OSI Approved :: MIT License
Classifier: Operating System :: OS Independent
Requires-Python: >=3.6
License-File: LICENSE
Requires-Dist: pandas>=1.0.0
Requires-Dist: numpy>=1.18.0
Requires-Dist: scikit-bio>=0.5.0
Requires-Dist: matplotlib
Requires-Dist: seaborn
Requires-Dist: paramiko>=2.7.0
Requires-Dist: pyyaml>=5.1
Requires-Dist: cryptography>=3.4.0
Requires-Dist: keyring>=23.0.0
Dynamic: author
Dynamic: author-email
Dynamic: classifier
Dynamic: description
Dynamic: description-content-type
Dynamic: home-page
Dynamic: license-file
Dynamic: requires-dist
Dynamic: requires-python
Dynamic: summary
